{
  "info": {
    "id": "tr",
    "name": "Turkish",
    "direction": "ltr",
    "author": "safa@teknobilgroup.com",
    "font": "Arial"
  },
  "words": {
    "global_all": "Herhangi biri",
    "global_username": "Kullanıcı adı",
    "global_expiration": "Süre sonu",
    "global_profile": "Profil",
    "global_firstname": "Ad",
    "global_lastname": "Soyadı",
    "global_available_balance": "Kullanılabilir Bakiye",
    "global_total": "Toplam",
    "global_reload": "Yeniden yükle",
    "global_download": "İndir",
    "global_date": "Tarih",
    "global_manager": "Yönetici",
    "global_price": "Fiyat",
    "global_filter_from_date": "Başlangıç Tarihi",
    "global_filter_to_date": "Tarihe",
    "global_filter_paid": "Paid",
    "global_filter_unpaid": "Unpaid",

    "global_ip": "IP",
    "global_description": "Açıklama",
    "global_comment": "Yorum",
    "global_filter_all_managers": "Tüm Yöneticiler",
    "global_filter_daily": "Günlük",
    "global_filter_monthly": "Aylık",
    "label_about": "Şirket",
    "label_about_hardware": "Donanım",
    "label_snono_messages": "Tedarikçi Mesajları",
    "label_welcome_screen_header": "Duyuru",
    "menu_dashboard": "Gösterge tablosu",
    "menu_settings": "Ayarlar",
    "menu_managers": "Yöneticiler",
    "menu_settings_general": "Genel Ayarlar",
    "menu_settings_acl": "Yetki Grupları",
    "menu_settings_ucp": "Kullanıcı Portalı",
    "menu_users": "Kullanıcılar",
    "menu_users_list": "Kullanıcı Listesi",
    "menu_users_online": "Çevrimiçi Kullanıcılar",
    "menu_users_tickets": "Destek Biletleri",
    "menu_nas": "NAS",
    "menu_profiles": "Profiller",
    "menu_profiles_list": "Profiller Listesi",
    "menu_profiles_pricing": "Fiyat Listesi",
    "menu_cards": "Kart Sistemi",
    "menu_settings_sites": "Siteler",
    "menu_reports": "Raporlar",
    "menu_reports_syslog": "Sistem Günlüğü",
    "menu_reports_managers_journal": "Yönetici Günlüğü",
    "menu_reports_managers_invoices": "Yönetici Faturaları",
    "menu_reports_managers_receipts": "Yönetici Faturaları",
    "menu_reports_user_auth_log": "Kullanıcı Yetkilendirme Günlüğü",
    "menu_reports_activations": "Aktivasyonlar",
    "menu_reports_activations_stats": "Aktivasyon İstatistikleri",
    "menu_reports_profits": "Karlar",
    "menu_reports_sessions": "Oturumlar",
    "menu_report_users": "Kullanıcılar",
    "menu_reports_traffic": "Trafik",
    "menu_reports_online": "Çevrimiçi Geçmiş",
    "menu_reports_money_transfer": "Para Transferleri",
    "menu_reports_cards_usage": "Kart Kullanımı",
    "menu_reports_radius_log": "Radius Günlüğü",
    "menu_tools": "Araçlar",
    "menu_tools_backup": "Yedekleme",
    "menu_tools_dashboard_manager": "Gösterge Tablosu Yöneticisi",
    "menu_tools_widget_factory": "Widget Fabrikası",
    "menu_tools_system_services": "Sistem Hizmetleri",
    "menu_tools_system_update": "Sistem Güncellemesi",
    "menu_tools_maintenance": "Bakım",
    "menu_tools_announcements": "Duyurular",
    "menu_tools_export": "Dışa aktar",
    "menu_tools_import": "Verileri İçe Aktar",
    "menu_tools_bulk_changes": "Toplu Değişiklikler",
    "menu_settings_freezone": "Serbest Bölge Ayarları",
    "menu_settings_sms": "Sms Ayarları",
    "menu_settings_email": "E-posta Ayarları",
    "menu_settings_email_template": "E-posta şablonları",
    "menu_settings_backup": "Yedekleme Ayarları",
    "menu_settings_license": "Lisans Ayarları",
    "menu_settings_notifications": "Bildirimler",
    "menu_settings_network": "Ağ Ayarları",
    "menu_settings_advanced": "Gelişmiş",
    "menu_settings_portal": "Web Portal",
    "menu_settings_sastrack": "SasTrack",
    "menu_settings_payment_gateways": "ödeme ağ geçitleri",
    "menu_settings_billing": "Faturalı faturalandırma",
    "menu_settings_telegram": "Telegram Ayarları",
    "menu_billing": "Faturalandırma",
    "menu_billing_user_invoices": "Kullanıcı Faturaları",
    "menu_billing_user_invoice_issue": "Fatura Düzenleme",
    "menu_ip_pools": "IP Havuzları",
    "menu_about": "Hakkında",
    "menu_bandwidth_controller": "Bant Genişliği Denetleyicisi",
    "menu_settings_usage_notifications": "data usage notifications",
    "managers_table_title": "Yönetici Listesi",
    "manager_table_balance": "Bakiye",
    "manager_table_group": "Grup",
    "manager_table_parent": "Üst",
    "manager_table_city": "Şehir",
    "manager_table_creation_date": "Oluşturma Tarihi",
    "manager_table_users_count": "Kullanıcılar",
    "manager_table_reward_points": "Ödül Puanları",
    "users_table_online_title": "Çevrimiçi Kullanıcılar",
    "users_table_title": "Kullanıcılar Tablosu",
    "users_table_status": "Durum",
    "users_table_username": "Kullanıcı adı",
    "users_table_firstname": "Ad",
    "users_table_lastname": "Soyadı",
    "users_table_expiration": "Süre sonu",
    "users_table_parent": "Üst",
    "users_table_profile": "Profil",
    "users_table_balance": "Bakiye",
    "users_table_daily_traffic": "Günlük Trafik",
    "users_table_city": "Şehir",
    "users_table_static_ip": "Statik IP",
    "users_table_notes": "Notlar",
    "users_table_last_online": "Son Çevrimiçi",
    "users_table_dl": "İndir",
    "users_table_ul": "Yükle",
    "users_table_daily_usage": "Günlük Kota",
    "users_table_uptime": "Çalışma süresi",
    "users_table_hardware": "Cihaz",
    "users_table_service_name": "Hizmet",
    "users_table_simultaneous_sessions": "Eşzamanlı Oturumlar",
    "users_table_company": "Şirket",
    "users_table_used_traffic": "Kullanılan Trafik",
    "users_table_phone": "Telefon",
    "users_table_address": "Adres",
    "users_tab_freezone_traffic": "FreeZone Trafiği",
    "users_action_activate": "Etkinleştir",
    "users_action_change_profile": "Profili Değiştir",
    "users_action_disconnect": "Bağlantıyı kes",
    "users_action_issue_invoice": "Fatura Düzenleme",
    "users_action_view": "Genel Bakış",
    "users_action_lock_mac": "MAC'i kilitle",
    "users_action_ping": "Ping",
    "users_action_extend": "Hizmeti Genişlet",
    "users_action_cancel": "Hizmeti İptal Et",
    "users_filter_status": "Durum",
    "users_filter_connection": "Bağlantı",
    "users_filter_profile": "Profil",
    "users_filter_profile_active": "Etkin Profil",
    "users_filter_parent": "Üst",
    "users_filter_sub_users": "Alt Kullanıcılar",
    "users_status_active": "Etkin",
    "users_status_expired": "Süresi dolmuş",
    "users_status_expiring_soon": "Yakında Sona Erecek",
    "users_status_expiring_today": "Bugün Süresi Doluyor",
    "users_status_online": "Çevrimiçi",
    "users_status_disabled": "Devre dışı",
    "users_status_traffic_depleted": "Bitti",
    "users_status_offline": "Çevrimdışı",
    "users_tab_overview": "Genel Bakış",
    "users_tab_edit": "Düzenle",
    "users_tab_traffic": "Trafik",
    "users_tab_sessions": "Oturumlar",
    "users_tab_invoices": "Faturalar",
    "users_tab_payments": "Ödemeler",
    "users_tab_history": "Geçmiş",
    "users_tab_documents": "Belgeler",
    "users_tab_radius": "RADIUS",
    "users_tab_journal": "Günlük",
    "user_depodrawal_form_title_withdrawal": "Tutar İndirimi",
    "user_depodrawal_form_title_deposit": "Para Yatırma Tutarı",
    "user_depodrawal_form_username": "Kullanıcı adı",
    "user_depodrawal_form_amount": "Tutar",
    "user_depodrawal_form_comment": "Yorum",
    "user_ping_dialog_title": "Ping Kullanıcısı",
    "user_form_label": "Kullanıcı Formu",
    "user_form_label_basic_information": "Temel Bilgiler",
    "user_form_label_username": "Kullanıcı adı",
    "user_form_label_enabled": "Etkin",
    "user_form_label_password": "Şifre",
    "user_form_label_password_confirm": "Parolayı Onayla",
    "user_form_label_profile": "Hizmet Profili",
    "user_form_label_parent": "Üst",
    "user_form_label_site": "Site",
    "user_form_label_mac_lock": "MAC Kilidi",
    "user_form_label_firstname": "Ad",
    "user_form_label_lastname": "Soyadı",
    "user_form_label_company": "Şirket",
    "user_form_label_email": "E-posta",
    "user_form_label_phone": "Telefon",
    "user_form_label_city": "Şehir",
    "user_form_label_address": "Adres",
    "user_form_label_apartment": "Daire",
    "user_form_label_street": "Sokak",
    "user_form_label_contract": "Sözleşme Kimliği",
    "user_form_label_national_id": "Kimlik No",
    "user_form_label_notes": "Notlar",
    "user_form_label_expiration": "Son kullanma tarihi",
    "user_form_label_user_type": "Kullanıcı Türü",
    "user_form_label_personnel_information": "Personel Bilgileri",
    "user_form_label_advanced": "Gelişmiş Ayrıntılar",
    "user_form_label_mac_list": "İzin verilen MAC'ler",
    "user_mac_dialog_title": "İzin Verilen MAC'ler",
    "user_mac_dialog_no_records": "Kayıt Bulunamadı",
    "user_rename_form_title": "Kullanıcıyı Yeniden Adlandır",
    "user_rename_form_current_username": "Mevcut Kullanıcı Adı",
    "user_rename_form_new_username": "Yeni Kullanıcı Adı",
    "user_overview_owner": "Sahip",
    "user_overview_profile": "Profil",
    "user_overview_expiration": "Süre sonu",
    "user_overview_pin_tries": "Yanlış PIN deniyor",
    "user_overview_status": "Durum",
    "user_overview_last_login": "Son Giriş",
    "user_overview_remaining_download": "Kalan İndirme",
    "user_overview_remaining_upload": "Kalan Yükleme",
    "user_overview_remaining_traffic": "Kalan Trafik",
    "user_overview_remaining_uptime": "Kalan Çalışma Süresi",
    "user_overview_purchases": "Toplam Satın Alma İşlemleri",
    "user_overview_created_on": "Oluşturma Tarihi",
    "user_overview_created_by": "Oluşturan",
    "user_activate_title": "Aktivasyon Bilgileri",
    "user_activate_username": "Kullanıcı adı",
    "user_activate_price": "Birim Fiyat",
    "user_activate_profile": "Profil",
    "user_activate_duration": "Süre",
    "user_activate_expiration": "Sona erme",
    "user_activate_download": "İndir (MB)",
    "user_activate_upload": "Yükle (MB)",
    "user_activate_balance": "Kullanılabilir Bakiye",
    "user_activate_user_balance": "Kullanıcı Bakiyesi",
    "user_activate_traffic": "Toplam Trafik",
    "user_activate_money_collected": "Toplanan Para",
    "user_activate_method": "Etkinleştirme Yöntemi",
    "user_activate_profile_description": "Profil Açıklaması",
    "user_activate_card_number": "Kart Numarası",
    "user_activate_vat": "KDV",
    "user_activate_required_amount": "Gerekli Miktar",
    "user_activate_total_required_amount": "Toplam Fiyat",
    "user_activate_success_activation": "Kullanıcılar Etkinleştirildi",
    "user_activate_fail_activation": "Kullanıcılar Etkinleştirilemedi",
    "user_activate_reward_points_given": "Ödül Puanları",
    "user_activate_reward_points_required": "Gerekli Noktalar",
    "user_activate_reward_points_balance": "Ödül Puanları Dengesi",
    "user_activate_rewards_title": "Ödül Puanları",
    "user_cancellation_form_title": "Hizmeti İptal Et",
    "user_cancellation_title": "İptal Ayrıntıları",
    "user_cancellation_last_price": "Son Etkinleştirme Fiyatı",
    "user_cancellation_activated_at": "Etkinleştirme Tarihi",
    "user_cancellation_remaining_days": "Kalan Günler",
    "user_cancellation_refund_amount": "Geri Ödeme Tutarı",
    "user_extend_form_title": "Hizmeti Genişlet",
    "user_extend_form_select_extension": "Uzantı Seçin",
    "user_extension_method": "Kullanarak Genişlet",
    "user_change_profile_title": "Kullanıcı Profilini Değiştir",
    "user_change_profile_expires_on": "Sona Erme Tarihi",
    "user_change_profile_new": "Yeni Profil",
    "user_change_profile_current": "Mevcut Profil",
    "user_change_type": "En Son Değişiklik",
    "user_change_warning1": "Kullanıcı zaten etkin. Profil değişikliği bir sonraki sona erme tarihinde uygulanacak",
    "user_change_warning2": "Kullanıcı zaten etkin. Profili değiştirmek geçerli hizmeti sonlandıracak ve kullanıcıyı sıfırlayacaktır",
    "user_change_option_immediate": "Hemen",
    "user_change_option_schedule": "Bir Sonraki Süre Sonu",
    "user_session_table_started": "Başladı",
    "user_session_table_ended": "Bitiş Tarihi",
    "user_session_table_ip": "IP",
    "user_session_table_download": "İndir",
    "user_session_table_upload": "Yükle",
    "user_session_table_mac": "MAC",
    "user_session_table_profile": "Profil",
    "user_session_table_service": "Hizmet",
    "user_session_table_protocol": "Protokol",
    "user_invoice_table_number": "Fatura No",
    "user_invoice_table_date": "Tarih",
    "user_invoice_table_type": "Tür",
    "user_invoice_table_amount": "Tutar",
    "user_invoice_table_description": "Açıklama",
    "user_invoice_table_username": "Kullanıcı adı",
    "user_invoice_table_created_by": "Oluşturan",
    "user_invoice_table_method": "Ödeme Yöntemi",
    "user_invoice_table_paid": "Ücretli",
    "user_receipt_table_no": "Makbuz No",
    "user_receipt_table_date": "Tarih",
    "user_receipt_table_type": "Tür",
    "user_receipt_table_amount": "Tutar",
    "user_receipt_table_description": "Açıklama",
    "user_receipt_table_created_by": "Oluşturan",
    "user_document_table_name": "Belge Adı",
    "user_document_table_size": "Boyut",
    "user_document_table_date": "Tarih",
    "user_history_table_date": "Tarih",
    "user_history_table_action": "Eylem",
    "user_history_table_description": "Açıklama",
    "user_history_table_created_by": "Oluşturan",
    "user_journal_table_date": "Tarih",
    "user_journal_table_cr": "CR",
    "user_journal_table_dr": "DR",
    "user_journal_table_amount": "Tutar",
    "user_journal_table_balance": "Bakiye",
    "user_journal_table_operation": "İşlem",
    "user_journal_table_description": "Açıklama",
    "nas_form_label1": "Temel Bilgiler",
    "nas_form_name": "Ad",
    "nas_form_enabled": "Etkin",
    "nas_form_ip_address": "IP Adresi",
    "nas_form_secret": "Paylaşılan Sır",
    "nas_form_type": "Tür",
    "nas_form_version": "Sürüm",
    "nas_form_api_username": "API Kullanıcı Adı",
    "nas_form_api_password": "API Parolası",
    "nas_form_coa_port": "Gelen (COA) Bağlantı Noktası",
    "nas_form_site": "Site",
    "nas_form_ip_accounting": "IP Hesabı",
    "nas_form_http_port": "HTTP Bağlantı Noktası",
    "nas_form_pool": "Havuz Adı ​​(isteğe bağlı)",
    "nas_form_description": "Açıklama",
    "nas_form_api_port": "API Bağlantı Noktası",
    "nas_form_monitor": "Monitör (ping)",
    "nas_form_snmp_community": "SNMP Topluluğu",
    "manager_form_label1": "Temel Bilgiler",
    "manager_form_username": "Kullanıcı adı",
    "manager_form_enabled": "Etkin",
    "manager_form_password": "Şifre",
    "manager_form_password_confirm": "Parolayı Onayla",
    "manager_form_security_group": "Güvenlik Grubu",
    "manager_form_parent": "Üst",
    "manager_form_label2": "Personel Bilgileri",
    "manager_form_firstname": "Ad",
    "manager_form_lastname": "Soyadı",
    "manager_form_company": "Şirket",
    "manager_form_email": "E-posta",
    "manager_form_phone": "Telefon",
    "manager_form_city": "Şehir",
    "manager_form_address": "Adres",
    "manager_form_notes": "Notlar",
    "manager_form_label3": "Gelişmiş Bilgiler",
    "manager_form_prefix": "Abone Öneki",
    "manager_form_suffix": "Abone Son Eki",
    "manager_form_max_users": "Maks. kullanıcı sayısı",
    "manager_form_site": "Site",
    "manager_form_deb_limit": "Borç Limiti",
    "manager_form_discount_rate": "İndirim Oranı (%)",
    "manager_form_label_allowed_ppp_services": "İzin Verilen PPP Hizmetleri",
    "manager_form_label4": "Manager Limits",
    "manager_form_limit_delete": "Limit Deletes",
    "manager_form_limit_rename": "Limit Renames",
    "manager_form_limit_profile_change": "Limit Profiles Changes",
    "manager_form_limit_delete_count": "Monthly Deletes",
    "manager_form_limit_rename_count": "Monthly Renames",
    "manager_form_limit_profile_change_count": "Monthly Profile Changes",
    "manager_form_limit_mac_change": "Limit MAC changes",
    "manager_form_limit_mac_change_count": "Monthly MAC Changes Limit",

    "manager_ppp_dialog_title": "İzin Verilen PPP Hizmetleri",
    "manager_tab_overview": "Genel Bakış",
    "manager_tab_edit": "Düzenle",
    "manager_tab_invoices": "Faturalar",
    "manager_tab_payments": "Makbuzlar",
    "yöneticiler_tab_journal": "Günlük",
    "manager_overview_balance": "Bakiye",
    "manager_overview_owner": "Sahip",
    "manager_overview_acl_group": "EKL Grubu",
    "manager_overview_status": "Durum",
    "manager_overview_total_users": "Toplam Kullanıcı",
    "manager_overview_active_users": "Etkin Kullanıcılar",
    "manager_overview_expired_users": "Süresi Dolmuş Kullanıcılar",
    "manager_overview_submanagers": "Alt Yöneticiler",
    "manager_overview_created_on": "Oluşturma Tarihi",
    "manager_overview_created_by": "Oluşturan",
    "manager_invoice_table_number": "Fatura No",
    "manager_invoice_table_date": "Tarih",
    "manager_invoice_table_type": "Tür",
    "manager_invoice_table_amount": "Tutar",
    "manager_invoice_table_description": "Açıklama",
    "manager_invoice_table_username": "Kullanıcı adı",
    "manager_invoice_table_created_by": "Oluşturan",
    "manager_invoice_table_method": "Ödeme Yöntemi",
    "manager_invoice_table_paid": "Ücretli",
    "manager_invoice_action_pay": "Fatura Ödeme",
    "prompt_invoices_pay": "Seçilen fatura ücretli olarak işaretlensin mi?",
    "manager_receipt_table_no": "Makbuz No",
    "manager_receipt_table_date": "Tarih",
    "manager_receipt_table_type": "Tür",
    "manager_receipt_table_amount": "Tutar",
    "manager_receipt_table_description": "Açıklama",
    "manager_receipt_table_created_by": "Oluşturan",
    "manager_journal_table_date": "Tarih",
    "manager_journal_table_cr": "CR",
    "manager_journal_table_dr": "DR",
    "manager_journal_table_amount": "Tutar",
    "manager_journal_table_balance": "Bakiye",
    "manager_journal_table_operation": "İşlem",
    "manager_journal_table_description": "Açıklama",
    "manager_depodrawal_form_title_withdrawal": "Tutar İndirimi",
    "manager_depodrawal_form_title_deposit": "Para Yatırma Tutarı",
    "manager_depodrawal_form_username": "Kullanıcı adı",
    "manager_depodrawal_form_amount": "Tutar",
    "manager_depodrawal_form_comment": "Yorum",
    "mangers_tree_title": "Yönetici Ağacı",
    "manager_rename_form_title": "Yöneticiyi Yeniden Adlandır",
    "manager_rename_form_current_username": "Mevcut Kullanıcı Adı",
    "manager_rename_form_new_username": "Yeni Kullanıcı Adı",
    "manager_profile_label_account": "Hesap Bilgileri",
    "manager_profile_label_image": "Profil Görüntüsü",
    "manager_profile_btn_password": "Parolayı Değiştir",
    "manager_profile_placeholder_new_password": "yeni şifre",
    "manager_profile_placeholder_confirm_password": "şifreyi onayla",
    "manager_profile_image_change": "değiştir",
    "manager_actions_add_reward_points": "Ödül Puanları Ekle",
    "manager_actions_deduct_reward_points": "Ödül Puanlarını İndir",
    "prm_any": "Kukla İzin",
    "prm_backup_create": "Yedekle - Oluştur",
    "prm_backup_delete": "Yedekle - Sil",
    "prm_backup_download": "Yedekle - İndir",
    "prm_backup_restore": "Yedekleme - Geri Yükleme",
    "prm_backup_upload": "Yedekle - Yükle",
    "prm_billing": "Faturalandırma",
    "prm_cards_change_owner": "Kartlar - Sahibini Değiştir",
    "prm_cards_delete": "Kartlar - Sil",
    "prm_cards_designer": "Kartlar - Tasarımcı",
    "prm_cards_download": "Kartlar - İndir",
    "prm_cards_generate_refill": "Kartlar - Yedek Kartlar Oluştur",
    "prm_cards_generate_user": "Kartlar - Ön Ödemeli Kullanıcı Kartları Oluştur",
    "prm_cards_job_cancel": "Kartlar - Üreteci İptal Et",
    "prm_cards_index": "Kartlar - Seri Dizini",
    "prm_cards_suspend_release": "Kartlar - Askıya Al ve Bırak",
    "prm_cards_list": "Kartlar - PIN'leri Listele",
    "prm_cards_verify": "Kartlar - Kartları Doğrula",
    "prm_dashboard_manager": "Gösterge Tablosu - Yönet",
    "prm_managers_change_self_password": "Yöneticiler - Kendi Parolanızı Değiştirin",
    "prm_managers_create": "Yöneticiler - Oluştur",
    "prm_managers_delete": "Yöneticiler - Sil",
    "prm_managers_deposit": "Yöneticiler - Para Yatır",
    "prm_managers_index": "Yöneticiler - Dizin",
    "prm_managers_index_all": "Yöneticiler - Dizin (Tüm Yöneticiler)",
    "prm_managers_invoice": "Yöneticiler - Faturaları Göster",
    "prm_managers_journal": "Yöneticiler - Günlüğü Göster",
    "prm_managers_login_as": "Yöneticiler - Farklı Giriş Yap (Tehlikeli!)",
    "prm_managers_receipt": "Yöneticiler - Makbuzları Göster",
    "prm_managers_sysadmin": "Yöneticiler - Sistem Yöneticisi",
    "prm_managers_update": "Yöneticiler - Düzenle / Güncelle",
    "prm_managers_withdrawal": "Yöneticiler - Para Çek",
    "prm_managers_export": "Yöneticiler - Excel'e Aktar",
    "prm_managers_rename": "Yöneticiler - Yeniden Adlandır",
    "prm_nas_create": "NAS - Oluştur",
    "prm_nas_delete": "NAS - Sil",
    "prm_nas_index": "NAS - Dizin",
    "prm_nas_update": "NAS - Güncelleme",
    "prm_nas_export": "NAS - Dışa Aktar",
    "prm_profiles_create": "Profiller - Oluştur",
    "prm_profiles_delete": "Profiller - Sil",
    "prm_profiles_index": "Profiller - Dizin",
    "prm_profiles_policy_manager": "Profiller - Politika Yöneticisi",
    "prm_profiles_pricing": "Profiller - Fiyatlandırma Yönetimi",
    "prm_profiles_update": "Profiller - Güncelleme",
    "prm_report_managers_invoices": "Raporlar - Yönetici Faturaları",
    "prm_report_managers_journal": "Raporlar - Yöneticiler Dergisi",
    "prm_report_syslog": "Raporlar - Sistem Günlüğü",
    "prm_journal_export": "Raporlar - Günlüğü Dışa Aktar",
    "prm_report_manager_auth_log": "Rapor - Kullanıcı Yetkilendirme Günlüğü",
    "prm_report_activations": "Rapor - Etkinleştirmeler",
    "prm_report_sessions": "Rapor - Oturumlar",
    "prm_report_users": "Rapor - Kullanıcılar",
    "prm_report_cards_usage": "Rapor - Kart Kullanımı",
    "prm_settings": "Ayarlar - Sistem Ayarları",
    "prm_sites_management": "Ayarlar - Site Yönetimi",
    "prm_tools_announcements": "Araçlar - Duyurular",
    "prm_tools_bandwidth_control": "Araçlar -> Bant Genişliği Kontrolü",
    "prm_ucp_activate": "Kullanıcı Kontrol Paneli - Etkinleştir",
    "prm_ucp_auto_login": "Kullanıcı Kontrol Paneli - Otomatik Giriş",
    "prm_ucp_billing": "Kullanıcı Kontrol Paneli - Faturalandırma",
    "prm_ucp_browse_packages": "Kullanıcı Kontrol Paneli - Paketleri Göster",
    "prm_ucp_cancel": "Kullanıcı Kontrol Paneli - Aboneliği İptal Et",
    "prm_ucp_change_info": "Kullanıcı Kontrol Paneli - Kullanıcı Bilgilerini Değiştir",
    "prm_ucp_change_password": "Kullanıcı Kontrol Paneli - Parolayı Değiştir",
    "prm_ucp_change_profile": "Kullanıcı Kontrol Paneli - Profili Değiştir",
    "prm_ucp_data_usage": "Kullanıcı Kontrol Paneli - Veri Kullanımını Göster",
    "prm_ucp_login": "Kullanıcı Kontrol Paneli - Oturum Açmaya İzin Ver",
    "prm_ucp_sessions": "Kullanıcı Kontrol Paneli - Oturumları Göster",
    "prm_ucp_support": "Kullanıcı Kontrol Paneli - Destek Biletlerini Gönder",
    "prm_ucp_extend": "Kullanıcı Kontrol Paneli - Kullanıcıları Genişlet",
    "prm_ucp_docs_show": "User Control Panel - Show Documents",
    "prm_ucp_docs_upload": "User Control Panel - Upload Documents",
    "prm_ucp_docs_delete" : "User Control Panel - Delete Documents",
    "prm_ucp_auto_renew": "User Control Panel - Enable/Disable Auto-Renew",

    "prm_users_activate": "Kullanıcılar - Etkinleştir",
    "prm_users_activate_card": "Kullanıcılar - Kupon kullanarak etkinleştir",
    "prm_users_activate_credit": "Kullanıcılar - Yönetici bakiyesini kullanarak etkinleştir",
    "prm_users_activate_trial": "Kullanıcılar - Test Hesabını Etkinleştir",
    "prm_users_activate_user_balance": "Kullanıcılar - Kullanıcı dengesini kullanarak etkinleştir",
    "prm_users_advanced": "Kullanıcılar - Gelişmiş Alanları Düzenle (tehlikeli!)",
    "prm_users_cancel_profile_change": "Kullanıcılar - Zamanlanmış Profil Değişikliğini İptal Et",
    "prm_users_change_profile": "Kullanıcılar - Profili Değiştir",
    "prm_users_change_profile_active": "Kullanıcılar - Etkin Kullanıcıların Profilini Değiştir",
    "prm_users_create": "Kullanıcılar - Oluştur",
    "prm_users_delete": "Kullanıcılar - Sil",
    "prm_users_deposit": "Kullanıcılar - Para Yatır",
    "prm_users_disconnect": "Kullanıcılar - Bağlantıyı Kes",
    "prm_users_history": "Kullanıcılar - Kullanıcı Geçmişini Göster",
    "prm_users_index": "Kullanıcılar - Dizin",
    "prm_users_index_all": "Kullanıcılar - Tüm Kullanıcıları Listele",
    "prm_users_invoice": "Kullanıcılar - Kullanıcı Faturalarını Göster",
    "prm_users_journal": "Kullanıcılar - Kullanıcı Günlüğünü Göster",
    "prm_users_mac_lock": "Kullanıcılar - MAC Kilidi Kullanıcısı",
    "prm_users_ping": "Kullanıcılar - Ping",
    "prm_users_rename": "Kullanıcılar - Yeniden Adlandır",
    "prm_users_reset_quota": "Kullanıcılar - Günlük Kotayı Sıfırla",
    "prm_users_sessions_index": "Kullanıcılar - Oturumları Göster",
    "prm_users_update": "Kullanıcılar - Güncelleme",
    "prm_users_withdrawal": "Kullanıcılar - Para Çekme",
    "prm_users_export": "Kullanıcılar - Excel'e Aktar",
    "prm_users_extend": "Kullanıcılar - Hizmeti Genişlet",
    "prm_users_cancel": "Kullanıcılar - Aboneliği İptal Et",
    "prm_users_reward_points": "Kullanıcılar - Ödül Puan Sistemi",
    "prm_users_pos": "Kullanıcılar - POS",
    "prm_users_live_traffic": "Kullanıcılar - Canlı Trafik Monitörü",
    "prm_users_delete_active": "Kullanıcılar - Etkin Kullanıcıları Sil",
    "prm_users_tickets": "Kullanıcılar - Destek Biletlerini Göster",
    "prm_users_freezone_traffic": "Kullanıcılar - Freezones Trafiğini Göster",
    "prm_users_show_password": "Users - Show Password",
    "prm_widget_factory": "Gösterge Tablosu - Pencere Öğeleri Fabrikası",
    "prm_tools_import": "Araçlar - Verileri İçe Aktar",
    "widget_title_total_users": "Toplam Kullanıcı",
    "widget_description_total_users": "Kayıtlı Kullanıcılar",
    "widget_title_managers": "Yöneticiler",
    "widget_description_managers": "",
    "widget_title_online_users": "Çevrimiçi Kullanıcılar",
    "widget_description_online_users": "Bağlı Kullanıcılar",
    "widget_title_active_users": "Etkin Kullanıcılar",
    "widget_description_active_users": "",
    "widget_title_expired_users": "Süresi Dolmuş Kullanıcılar",
    "widget_description_expired_users": "",
    "widget_title_about_expire": "Süresi Dolmak üzere",
    "widget_description_about_expire": "3 gün içinde süresi dolan kullanıcılar",
    "widget_title_balance": "Bakiye",
    "widget_description_balance": "",
    "widget_title_system_version": "Sistem Sürümü",
    "widget_description_system_version": "SAS sürümü",
    "widget_title_uptime": "Sistem Çalışma Süresi",
    "widget_description_uptime": "",
    "widget_title_memory": "Sistem Belleği",
    "widget_description_memory": "Kullanılan Bellek",
    "widget_title_disk": "Sistem Diski",
    "widget_description_disk": "Kullanılan Sistem Diski",
    "widget_title_ping": "Ağ",
    "widget_description_ping": "Snono Sistemlerinde Ping",
    "widget_title_ping_dns": "DNS Ping",
    "widget_description_ping_dns": "1.1.1.1'deki Ping",
    "widget_title_ping_google": "Google Ping",
    "widget_description_ping_google": "Google.com'da ping",
    "widget_title_reward_points": "Ödül Puanları",
    "widget_description_reward_points": "",
    "widget_title_fup_online": "Çevrimiçi FUP",
    "widget_description_fup_online": "",
    "widget_title_system_time": "Sistem Saati",
    "widget_description_system_time": "",
    "user_activate_form_title": "Kullanıcıyı Etkinleştir",
    "user_activate_option_manager_balance": "Yönetici Bakiyesi",
    "user_activate_option_user_balance": "Kullanıcı Bakiyesi",
    "user_activate_option_user_card": "Ön Ödemeli Kart",
    "user_activate_option_reward_points": "Ödül Puanları",
    "ippool_form_title": "Havuz Ekle / Düzenle",
    "ippool_form_name": "Havuz Adı",
    "ippool_form_start_ip": "IP'yi başlat",
    "ippool_form_end_ip": "Son IP",
    "ippool_form_lease_time": "Kiralama Süresi (saat)",
    "report_users_per_manager_title": "Yönetici Başına Kullanıcı",
    "report_users_per_profile_title": "Profil Başına Kullanıcı",
    "report_users_registrations_title": "Kayıtlar",
    "report_users_registrations_per_month": "Aylık Kayıt",
    "header_account": "Hesap",
    "header_profile": "Profil",
    "header_login_as": "Farklı Oturum Aç ...",
    "header_logout": "Çıkış",
    "header_self_deposit": "Para Yatırma",
    "global_actions_new": "Yeni",
    "global_actions_live_traffic": "Canlı Trafik",
    "global_actions_edit": "Düzenle",
    "global_actions_edit_new_tab": "Düzenle (Yeni Sekme)",
    "global_actions_rename": "Yeniden adlandır",
    "global_actions_deposit": "Para Yatırma",
    "global_actions_withdrawal": "Para çekme",
    "global_actions_delete": "Sil",
    "global_table_actions": "İşlemler",
    "global_table_label_found": "Bulundu",
    "global_table_label_records": "kayıt (lar)",
    "global_label_username": "Kullanıcı adı",
    "global_label_password": "Şifre",
    "global_label_balance": "Bakiye",
    "global_label_advanced_filter": "Gelişmiş Filtre",
    "global_label_profile": "Profil",
    "global_button_dismiss": "Kapat",
    "global_button_submit": "Gönder",
    "global_button_activate": "Etkinleştir",
    "global_button_search": "Ara",
    "global_button_refund": "Geri Ödeme",
    "global_label_download": "İndir",
    "global_label_upload": "Yükle",
    "global_label_rename": "Yeniden adlandır",
    "global_label_delete": "Sil",
    "global_user_control_panel": "Kullanıcı Kontrol Paneli",
    "user_invoice_title_action": "Fatura Tasarımcısı",
    "placeholder_search": "Ara ...",
    "rsp_save_success": "Başarıyla Kaydedildi",
    "rsp_success": "Değişiklikler Başarıyla Uygulandı",
    "rsp_update_success": "Başarıyla Güncellendi",
    "rsp_insicient_balance": "Yetersiz Bakiye",
    "rsp_amount_deducted": "Kesinti Tutarı",
    "rsp_amount_added": "Eklenen Tutar",
    "rsp_exceeded_max_users": "Kullanıcı Sınırını Aştı",
    "rsp_user_exists": "Kullanıcı Zaten Var",
    "rsp_profile_changed": "Profil Değişti",
    "rsp_profile_change_scheduled": "Profil Değişiklik Planlandı",
    "msg_manager_activate_success": "Kullanıcı Başarıyla Etkinleştirildi",
    "msg_wait": "Lütfen Bekleyin ...",
    "msg_update_success": "Kullanıcı Başarıyla Güncellendi",
    "msg_manager_rename_success": "Yönetici Yeniden Adlandı",
    "msg_manager_rename_error": "Yönetici yeniden adlandırılamıyor",
    "msg_manager_delete_success": "Yönetici Silindi",
    "msg_manager_delete_warning": "Bazı yöneticiler silinemiyor",
    "msg_user_rename_success": "Kullanıcı Yeniden Adlandırıldı",
    "msg_user_rename_error": "Kullanıcı yeniden adlandırılamıyor",
    "msg_user_delete_success": "Kullanıcılar Silindi",
    "msg_user_delete_warning": "Bazı kullanıcılar silinemiyor",
    "msg_user_not_online": "Kullanıcı Çevrimiçi Değil",
    "msg_invoice_already_paid": "Fatura zaten ödendi",
    "msg_user_activate_success": "Kullanıcı Etkin",
    "msg_user_already_active": "Kullanıcı aktif, profili değiştirmesine izin verilmiyor",
    "prompt_delete_manager": "Seçilen yöneticiler silinsin mi?",
    "prompt_delete_user": "Seçilen kullanıcılar silinsin mi?",
    "prompt_disconnect_user": "Seçilen Kullanıcının Bağlantısı Kesilsin mi?",
    "prompt_lock_mac": "Geçerli MAC'de kullanıcı kilitlensin mi?",
    "report_activations_title": "Aktivasyon Raporu",
    "report_activations_chart_title": "Aktivasyon Şeması",
    "report_activations_old_expiration": "Eski Sona Erme",
    "report_activations_new_expiration": "Yeni Süre Sonu",
    "report_syslog_title": "Sistem Günlüğü",
    "report_syslog_event": "Etkinlik",
    "report_user_auth_log_title": "Kullanıcı Kimlik Doğrulama Günlüğü",
    "report_journal_manager_title": "Yönetici Günlüğü",
    "report_journal_cr": "Kredi",
    "report_journal_dr": "Borç",
    "report_journal_amount": "Tutar",
    "report_journal_balance": "Bakiye",
    "report_profits_title": "Kar Grafiği",
    "user_live_traffic_chart_title": "Canlı Trafik",
    "tickets_action_close": "Bileti Kapat",
    "self_deposit_method": "Ödeme Yöntemi",
    "self_deposit_select_method": "Ödeme Yöntemini Seç",
    "self_deposit_amount": "Para Yatırma Tutarı",
    "self_deposit_deposit_button": "Para Yatırma",
    "self_deposit_no_payment_method": "Ödeme Yöntemi Mevcut Değil",
    "self_deposit_kushok_voucher": "Kupon PIN'i",

    "invoice_type_activate": "Activation",
    "invoice_type_deposit": "Deposit",
    "invoice_type_commission": "Commission",
    "invoice_type_transfer_deposit": "User Deposit",
    "invoice_type_transfer_withdrawal": "User Withdrawal",
    "invoice_type_withdrawal": "Withdrawal",

    "aboard_label_subscribers": "Subscribers",
    "aboard_label_online_users": "Online Users",
    "aboard_label_finance": "Finance & Sales",
    "aboard_label_system_health": "System Health",
    "aboard_label_cpu": "CPU Load",
    "aboard_label_memory": "Memory Usage",
    "aboard_label_disk": "Disk Usage",
    "aboard_label_db_time": "Database Time",
    "aboard_label_timezone": "Time Zone"
  }
}

